[{"player": "ACT"}, {"player": "DIRECTION"}, {"player": "EGEON"}, {"player": "DUKE"}, {"player": "JAILER"}, {"player": "SCENE"}, {"player": "FIRST MERCHANT"}, {"player": "ANTIPHOLUS OF SYRACUSE"}, {"player": "DROMIO OF SYRACUSE"}, {"player": "DROMIO OF EPHESUS"}, {"player": "ADRIANA"}, {"player": "LUCIANA"}, {"player": "ANTIPHOLUS OF EPHESUS"}, {"player": "BALTHASAR"}, {"player": "LUCE"}, {"player": "ANGELO"}, {"player": "SECOND MERCHANT"}, {"player": "OFFICER"}, {"player": "COURTESAN"}, {"player": "PINCH"}, {"player": "ABBESS"}, {"player": "MESSENGER"}]