[{"player": "ACT", "playerline": "ACT III"}, {"player": "SCENE", "playerline": "SCENE I"}, {"player": "DIRECTION", "playerline": "[Enter Duke as a Friar, Claudio, and Provost.]"}, {"player": "DUKE", "playerline": "So then you hope of pardon from Lord Angelo?"}, {"player": "CLAUDIO", "playerline": "The miserable have no other medicine"}, {"player": "CLAUDIO", "playerline": "But only hope."}, {"player": "CLAUDIO", "playerline": "I have hope to live and am prepared to die."}, {"player": "DUKE", "playerline": "Be absolute for death. Either death or life"}, {"player": "DUKE", "playerline": "Shall thereby be the sweeter. Reason thus with life:"}, {"player": "DUKE", "playerline": "If I do lose thee, I do lose a thing"}, {"player": "DUKE", "playerline": "That none but fools would keep. A breath thou art,"}, {"player": "DUKE", "playerline": "Servile to all the skyey influences"}, {"player": "DUKE", "playerline": "That doth this habitation where thou keep'st"}, {"player": "DUKE", "playerline": "Hourly afflict. Merely, thou art death's fool,"}, {"player": "DUKE", "playerline": "For him thou labor'st by thy flight to shun,"}, {"player": "DUKE", "playerline": "And yet runn'st toward him still. Thou art not noble,"}, {"player": "DUKE", "playerline": "For all th' accommodations that thou bear'st"}, {"player": "DUKE", "playerline": "Are nursed by baseness. Thou 'rt by no means valiant,"}, {"player": "DUKE", "playerline": "For thou dost fear the soft and tender fork"}, {"player": "DUKE", "playerline": "Of a poor worm. Thy best of rest is sleep,"}, {"player": "DUKE", "playerline": "And that thou oft provok'st, yet grossly fear'st"}, {"player": "DUKE", "playerline": "Thy death, which is no more. Thou art not thyself,"}, {"player": "DUKE", "playerline": "For thou exists on many a thousand grains"}, {"player": "DUKE", "playerline": "That issue out of dust. Happy thou art not,"}, {"player": "DUKE", "playerline": "For what thou hast not, still thou striv'st to get,"}, {"player": "DUKE", "playerline": "And what thou hast, forget'st. Thou art not certain,"}, {"player": "DUKE", "playerline": "For thy complexion shifts to strange effects"}, {"player": "DUKE", "playerline": "After the moon. If thou art rich, thou 'rt poor,"}, {"player": "DUKE", "playerline": "For, like an ass whose back with ingots bows,"}, {"player": "DUKE", "playerline": "Thou bear'st thy heavy riches but a journey,"}, {"player": "DUKE", "playerline": "And death unloads thee. Friend hast thou none,"}, {"player": "DUKE", "playerline": "For thine own bowels which do call thee sire,"}, {"player": "DUKE", "playerline": "The mere effusion of thy proper loins,"}, {"player": "DUKE", "playerline": "Do curse the gout, serpigo, and the rheum"}, {"player": "DUKE", "playerline": "For ending thee no sooner. Thou hast nor youth nor age,"}, {"player": "DUKE", "playerline": "But as it were an after-dinner's sleep"}, {"player": "DUKE", "playerline": "Dreaming on both, for all thy blessed youth"}, {"player": "DUKE", "playerline": "Becomes as aged and doth beg the alms"}, {"player": "DUKE", "playerline": "Of palsied eld; and when thou art old and rich,"}, {"player": "DUKE", "playerline": "Thou hast neither heat, affection, limb, nor beauty"}, {"player": "DUKE", "playerline": "To make thy riches pleasant. What's yet in this"}, {"player": "DUKE", "playerline": "That bears the name of life? Yet in this life"}, {"player": "DUKE", "playerline": "Lie hid more thousand deaths; yet death we fear,"}, {"player": "DUKE", "playerline": "That makes these odds all even."}, {"player": "CLAUDIO", "playerline": "I humbly thank you."}, {"player": "CLAUDIO", "playerline": "To sue to live, I find I seek to die,"}, {"player": "CLAUDIO", "playerline": "And seeking death, find life. Let it come on."}, {"player": "ISABELLA", "playerline": "What ho! Peace here, grace, and good company."}, {"player": "PROVOST", "playerline": "Who's there? Come in. The wish deserves a welcome."}, {"player": "DUKE", "playerline": "Dear sir, ere long I'll visit you again."}, {"player": "CLAUDIO", "playerline": "Most holy sir, I thank you."}, {"player": "DIRECTION", "playerline": "[Enter Isabella.]"}, {"player": "ISABELLA", "playerline": "My business is a word or two with Claudio."}, {"player": "PROVOST", "playerline": "And very welcome.--Look, signior, here's your sister."}, {"player": "DUKE", "playerline": "Provost, a word with you."}, {"player": "PROVOST", "playerline": "As many as you please."}, {"player": "DUKE", "playerline": "Bring me to hear them speak, where I may be concealed."}, {"player": "DIRECTION", "playerline": "[Duke and Provost exit.]"}, {"player": "CLAUDIO", "playerline": "Now, sister, what's the comfort?"}, {"player": "ISABELLA", "playerline": "Why,"}, {"player": "ISABELLA", "playerline": "As all comforts are, most good, most good indeed."}, {"player": "ISABELLA", "playerline": "Lord Angelo, having affairs to heaven,"}, {"player": "ISABELLA", "playerline": "Intends you for his swift ambassador,"}, {"player": "ISABELLA", "playerline": "Where you shall be an everlasting leiger;"}, {"player": "ISABELLA", "playerline": "Therefore your best appointment make with speed."}, {"player": "ISABELLA", "playerline": "Tomorrow you set on."}, {"player": "CLAUDIO", "playerline": "Is there no remedy?"}, {"player": "ISABELLA", "playerline": "None but such remedy as, to save a head,"}, {"player": "ISABELLA", "playerline": "To cleave a heart in twain."}, {"player": "CLAUDIO", "playerline": "But is there any?"}, {"player": "ISABELLA", "playerline": "Yes, brother, you may live."}, {"player": "ISABELLA", "playerline": "There is a devilish mercy in the judge,"}, {"player": "ISABELLA", "playerline": "If you'll implore it, that will free your life"}, {"player": "ISABELLA", "playerline": "But fetter you till death."}, {"player": "CLAUDIO", "playerline": "Perpetual durance?"}, {"player": "ISABELLA", "playerline": "Ay, just; perpetual durance, a restraint,"}, {"player": "ISABELLA", "playerline": "Though all the world's vastidity you had,"}, {"player": "ISABELLA", "playerline": "To a determined scope."}, {"player": "CLAUDIO", "playerline": "But in what nature?"}, {"player": "ISABELLA", "playerline": "In such a one as, you consenting to 't,"}, {"player": "ISABELLA", "playerline": "Would bark your honor from that trunk you bear"}, {"player": "ISABELLA", "playerline": "And leave you naked."}, {"player": "CLAUDIO", "playerline": "Let me know the point."}, {"player": "ISABELLA", "playerline": "O, I do fear thee, Claudio, and I quake"}, {"player": "ISABELLA", "playerline": "Lest thou a feverous life shouldst entertain,"}, {"player": "ISABELLA", "playerline": "And six or seven winters more respect"}, {"player": "ISABELLA", "playerline": "Than a perpetual honor. Dar'st thou die?"}, {"player": "ISABELLA", "playerline": "The sense of death is most in apprehension,"}, {"player": "ISABELLA", "playerline": "And the poor beetle that we tread upon"}, {"player": "ISABELLA", "playerline": "In corporal sufferance finds a pang as great"}, {"player": "ISABELLA", "playerline": "As when a giant dies."}, {"player": "CLAUDIO", "playerline": "Why give you me this shame?"}, {"player": "CLAUDIO", "playerline": "Think you I can a resolution fetch"}, {"player": "CLAUDIO", "playerline": "From flowery tenderness? If I must die,"}, {"player": "CLAUDIO", "playerline": "I will encounter darkness as a bride,"}, {"player": "CLAUDIO", "playerline": "And hug it in mine arms."}, {"player": "ISABELLA", "playerline": "There spake my brother! There my father's grave"}, {"player": "ISABELLA", "playerline": "Did utter forth a voice. Yes, thou must die."}, {"player": "ISABELLA", "playerline": "Thou art too noble to conserve a life"}, {"player": "ISABELLA", "playerline": "In base appliances. This outward-sainted deputy--"}, {"player": "ISABELLA", "playerline": "Whose settled visage and deliberate word"}, {"player": "ISABELLA", "playerline": "Nips youth i' th' head, and follies doth enew"}, {"player": "ISABELLA", "playerline": "As falcon doth the fowl--is yet a devil."}, {"player": "ISABELLA", "playerline": "His filth within being cast, he would appear"}, {"player": "ISABELLA", "playerline": "A pond as deep as hell."}, {"player": "CLAUDIO", "playerline": "The prenzie Angelo?"}, {"player": "ISABELLA", "playerline": "O, 'tis the cunning livery of hell"}, {"player": "ISABELLA", "playerline": "The damned'st body to invest and cover"}, {"player": "ISABELLA", "playerline": "In prenzie guards. Dost thou think, Claudio,"}, {"player": "ISABELLA", "playerline": "If I would yield him my virginity"}, {"player": "ISABELLA", "playerline": "Thou mightst be freed?"}, {"player": "CLAUDIO", "playerline": "O heavens, it cannot be!"}, {"player": "ISABELLA", "playerline": "Yes, he would give 't thee; from this rank offense,"}, {"player": "ISABELLA", "playerline": "So to offend him still. This night's the time"}, {"player": "ISABELLA", "playerline": "That I should do what I abhor to name,"}, {"player": "ISABELLA", "playerline": "Or else thou diest tomorrow."}, {"player": "CLAUDIO", "playerline": "Thou shalt not do 't."}, {"player": "ISABELLA", "playerline": "O, were it but my life,"}, {"player": "ISABELLA", "playerline": "I'd throw it down for your deliverance"}, {"player": "ISABELLA", "playerline": "As frankly as a pin."}, {"player": "CLAUDIO", "playerline": "Thanks, dear Isabel."}, {"player": "ISABELLA", "playerline": "Be ready, Claudio, for your death tomorrow."}, {"player": "CLAUDIO", "playerline": "Yes. Has he affections in him"}, {"player": "CLAUDIO", "playerline": "That thus can make him bite the law by th' nose,"}, {"player": "CLAUDIO", "playerline": "When he would force it? Sure it is no sin,"}, {"player": "CLAUDIO", "playerline": "Or of the deadly seven it is the least."}, {"player": "ISABELLA", "playerline": "Which is the least?"}, {"player": "CLAUDIO", "playerline": "If it were damnable, he being so wise,"}, {"player": "CLAUDIO", "playerline": "Why would he for the momentary trick"}, {"player": "CLAUDIO", "playerline": "Be perdurably fined? O, Isabel--"}, {"player": "ISABELLA", "playerline": "What says my brother?"}, {"player": "CLAUDIO", "playerline": "Death is a fearful thing."}, {"player": "ISABELLA", "playerline": "And shamed life a hateful."}, {"player": "CLAUDIO", "playerline": "Ay, but to die, and go we know not where,"}, {"player": "CLAUDIO", "playerline": "To lie in cold obstruction and to rot,"}, {"player": "CLAUDIO", "playerline": "This sensible warm motion to become"}, {"player": "CLAUDIO", "playerline": "A kneaded clod; and the delighted spirit"}, {"player": "CLAUDIO", "playerline": "To bathe in fiery floods, or to reside"}, {"player": "CLAUDIO", "playerline": "In thrilling region of thick-ribbed ice,"}, {"player": "CLAUDIO", "playerline": "To be imprisoned in the viewless winds"}, {"player": "CLAUDIO", "playerline": "And blown with restless violence round about"}, {"player": "CLAUDIO", "playerline": "The pendent world; or to be worse than worst"}, {"player": "CLAUDIO", "playerline": "Of those that lawless and incertain thought"}, {"player": "CLAUDIO", "playerline": "Imagine howling--'tis too horrible."}, {"player": "CLAUDIO", "playerline": "The weariest and most loathed worldly life"}, {"player": "CLAUDIO", "playerline": "That age, ache, penury, and imprisonment"}, {"player": "CLAUDIO", "playerline": "Can lay on nature is a paradise"}, {"player": "CLAUDIO", "playerline": "To what we fear of death."}, {"player": "ISABELLA", "playerline": "Alas, alas!"}, {"player": "CLAUDIO", "playerline": "Sweet sister, let me live."}, {"player": "CLAUDIO", "playerline": "What sin you do to save a brother's life,"}, {"player": "CLAUDIO", "playerline": "Nature dispenses with the deed so far"}, {"player": "CLAUDIO", "playerline": "That it becomes a virtue."}, {"player": "ISABELLA", "playerline": "O, you beast!"}, {"player": "ISABELLA", "playerline": "O faithless coward, O dishonest wretch,"}, {"player": "ISABELLA", "playerline": "Wilt thou be made a man out of my vice?"}, {"player": "ISABELLA", "playerline": "Is 't not a kind of incest to take life"}, {"player": "ISABELLA", "playerline": "From thine own sister's shame? What should I think?"}, {"player": "ISABELLA", "playerline": "Heaven shield my mother played my father fair,"}, {"player": "ISABELLA", "playerline": "For such a warped slip of wilderness"}, {"player": "ISABELLA", "playerline": "Ne'er issued from his blood. Take my defiance;"}, {"player": "ISABELLA", "playerline": "Die, perish. Might but my bending down"}, {"player": "ISABELLA", "playerline": "Reprieve thee from thy fate, it should proceed."}, {"player": "ISABELLA", "playerline": "I'll pray a thousand prayers for thy death,"}, {"player": "ISABELLA", "playerline": "No word to save thee."}, {"player": "CLAUDIO", "playerline": "Nay, hear me, Isabel--"}, {"player": "ISABELLA", "playerline": "O, fie, fie, fie!"}, {"player": "ISABELLA", "playerline": "Thy sin's not accidental, but a trade."}, {"player": "ISABELLA", "playerline": "Mercy to thee would prove itself a bawd."}, {"player": "ISABELLA", "playerline": "'Tis best that thou diest quickly."}, {"player": "CLAUDIO", "playerline": "O, hear me, Isabella--"}, {"player": "DIRECTION", "playerline": "[Enter Duke as a Friar.]"}, {"player": "DUKE", "playerline": "Vouchsafe a word, young sister, but one word."}, {"player": "ISABELLA", "playerline": "What is your will?"}, {"player": "DUKE", "playerline": "Might you dispense with your leisure, I"}, {"player": "DUKE", "playerline": "would by and by have some speech with you. The"}, {"player": "DUKE", "playerline": "satisfaction I would require is likewise your own benefit."}, {"player": "ISABELLA", "playerline": "I have no superfluous leisure. My stay must"}, {"player": "ISABELLA", "playerline": "be stolen out of other affairs, but I will attend you awhile."}, {"player": "DUKE", "playerline": "Son, I have overheard"}, {"player": "DUKE", "playerline": "what hath passed between you and your"}, {"player": "DUKE", "playerline": "sister. Angelo had never the purpose to corrupt her;"}, {"player": "DUKE", "playerline": "only he hath made an assay of her virtue, to practice"}, {"player": "DUKE", "playerline": "his judgment with the disposition of natures. She,"}, {"player": "DUKE", "playerline": "having the truth of honor in her, hath made him"}, {"player": "DUKE", "playerline": "that gracious denial which he is most glad to"}, {"player": "DUKE", "playerline": "receive. I am confessor to Angelo, and I know this"}, {"player": "DUKE", "playerline": "to be true. Therefore prepare yourself to death. Do"}, {"player": "DUKE", "playerline": "not satisfy your resolution with hopes that are"}, {"player": "DUKE", "playerline": "fallible. Tomorrow you must die. Go to your knees"}, {"player": "DUKE", "playerline": "and make ready."}, {"player": "CLAUDIO", "playerline": "Let me ask my sister pardon. I am so out of"}, {"player": "CLAUDIO", "playerline": "love with life that I will sue to be rid of it."}, {"player": "DUKE", "playerline": "Hold you there. Farewell.--Provost, a"}, {"player": "DUKE", "playerline": "word with you."}, {"player": "DIRECTION", "playerline": "[Enter Provost.]"}, {"player": "PROVOST", "playerline": "What's your will, father?"}, {"player": "DUKE", "playerline": "That now you are come, you will be"}, {"player": "DUKE", "playerline": "gone. Leave me awhile with the maid. My mind"}, {"player": "DUKE", "playerline": "promises with my habit no loss shall touch her by"}, {"player": "DUKE", "playerline": "my company."}, {"player": "PROVOST", "playerline": "In good time."}, {"player": "DUKE", "playerline": "The hand that hath made"}, {"player": "DUKE", "playerline": "you fair hath made you good. The goodness that is"}, {"player": "DUKE", "playerline": "cheap in beauty makes beauty brief in goodness,"}, {"player": "DUKE", "playerline": "but grace, being the soul of your complexion, shall"}, {"player": "DUKE", "playerline": "keep the body of it ever fair. The assault that Angelo"}, {"player": "DUKE", "playerline": "hath made to you, fortune hath conveyed to my"}, {"player": "DUKE", "playerline": "understanding; and but that frailty hath examples"}, {"player": "DUKE", "playerline": "for his falling, I should wonder at Angelo. How will"}, {"player": "DUKE", "playerline": "you do to content this substitute and to save your brother?"}, {"player": "ISABELLA", "playerline": "I am now going to resolve him. I had rather"}, {"player": "ISABELLA", "playerline": "my brother die by the law than my son should be"}, {"player": "ISABELLA", "playerline": "unlawfully born. But, O, how much is the good"}, {"player": "ISABELLA", "playerline": "duke deceived in Angelo! If ever he return, and I"}, {"player": "ISABELLA", "playerline": "can speak to him, I will open my lips in vain, or"}, {"player": "ISABELLA", "playerline": "discover his government."}, {"player": "DUKE", "playerline": "That shall not be much amiss. Yet, as"}, {"player": "DUKE", "playerline": "the matter now stands, he will avoid your accusation:"}, {"player": "DUKE", "playerline": "he made trial of you only. Therefore, fasten"}, {"player": "DUKE", "playerline": "your ear on my advisings. To the love I have in doing"}, {"player": "DUKE", "playerline": "good, a remedy presents itself. I do make myself"}, {"player": "DUKE", "playerline": "believe that you may most uprighteously do a poor"}, {"player": "DUKE", "playerline": "wronged lady a merited benefit, redeem your brother"}, {"player": "DUKE", "playerline": "from the angry law, do no stain to your own"}, {"player": "DUKE", "playerline": "gracious person, and much please the absent duke,"}, {"player": "DUKE", "playerline": "if peradventure he shall ever return to have hearing"}, {"player": "DUKE", "playerline": "of this business."}, {"player": "ISABELLA", "playerline": "Let me hear you speak farther. I have spirit to"}, {"player": "ISABELLA", "playerline": "do anything that appears not foul in the truth of my"}, {"player": "ISABELLA", "playerline": "spirit."}, {"player": "DUKE", "playerline": "Virtue is bold, and goodness never"}, {"player": "DUKE", "playerline": "fearful. Have you not heard speak of Mariana, the"}, {"player": "DUKE", "playerline": "sister of Frederick, the great soldier who miscarried"}, {"player": "DUKE", "playerline": "at sea?"}, {"player": "ISABELLA", "playerline": "I have heard of the lady, and good words"}, {"player": "ISABELLA", "playerline": "went with her name."}, {"player": "DUKE", "playerline": "She should this Angelo have married,"}, {"player": "DUKE", "playerline": "was affianced to her oath, and the nuptial appointed."}, {"player": "DUKE", "playerline": "Between which time of the contract and"}, {"player": "DUKE", "playerline": "limit of the solemnity, her brother Frederick was"}, {"player": "DUKE", "playerline": "wracked at sea, having in that perished vessel the"}, {"player": "DUKE", "playerline": "dowry of his sister. But mark how heavily this befell"}, {"player": "DUKE", "playerline": "to the poor gentlewoman. There she lost a noble"}, {"player": "DUKE", "playerline": "and renowned brother, in his love toward her ever"}, {"player": "DUKE", "playerline": "most kind and natural; with him, the portion and"}, {"player": "DUKE", "playerline": "sinew of her fortune, her marriage dowry; with"}, {"player": "DUKE", "playerline": "both, her combinate husband, this well-seeming Angelo."}, {"player": "ISABELLA", "playerline": "Can this be so? Did Angelo so leave her?"}, {"player": "DUKE", "playerline": "Left her in her tears and dried not one"}, {"player": "DUKE", "playerline": "of them with his comfort, swallowed his vows"}, {"player": "DUKE", "playerline": "whole, pretending in her discoveries of dishonor; in"}, {"player": "DUKE", "playerline": "few, bestowed her on her own lamentation, which"}, {"player": "DUKE", "playerline": "she yet wears for his sake; and he, a marble to her"}, {"player": "DUKE", "playerline": "tears, is washed with them but relents not."}, {"player": "ISABELLA", "playerline": "What a merit were it in death to take this"}, {"player": "ISABELLA", "playerline": "poor maid from the world! What corruption in this"}, {"player": "ISABELLA", "playerline": "life, that it will let this man live! But how out of this"}, {"player": "ISABELLA", "playerline": "can she avail?"}, {"player": "DUKE", "playerline": "It is a rupture that you may easily heal,"}, {"player": "DUKE", "playerline": "and the cure of it not only saves your brother, but"}, {"player": "DUKE", "playerline": "keeps you from dishonor in doing it."}, {"player": "ISABELLA", "playerline": "Show me how, good father."}, {"player": "DUKE", "playerline": "This forenamed maid hath yet in her"}, {"player": "DUKE", "playerline": "the continuance of her first affection. His unjust"}, {"player": "DUKE", "playerline": "unkindness, that in all reason should have"}, {"player": "DUKE", "playerline": "quenched her love, hath, like an impediment in the"}, {"player": "DUKE", "playerline": "current, made it more violent and unruly. Go you to"}, {"player": "DUKE", "playerline": "Angelo, answer his requiring with a plausible obedience,"}, {"player": "DUKE", "playerline": "agree with his demands to the point. Only"}, {"player": "DUKE", "playerline": "refer yourself to this advantage: first, that your stay"}, {"player": "DUKE", "playerline": "with him may not be long, that the time may have all"}, {"player": "DUKE", "playerline": "shadow and silence in it, and the place answer to"}, {"player": "DUKE", "playerline": "convenience. This being granted in course, and"}, {"player": "DUKE", "playerline": "now follows all: we shall advise this wronged maid"}, {"player": "DUKE", "playerline": "to stead up your appointment, go in your place. If"}, {"player": "DUKE", "playerline": "the encounter acknowledge itself hereafter, it may"}, {"player": "DUKE", "playerline": "compel him to her recompense; and here, by this, is"}, {"player": "DUKE", "playerline": "your brother saved, your honor untainted, the poor"}, {"player": "DUKE", "playerline": "Mariana advantaged, and the corrupt deputy"}, {"player": "DUKE", "playerline": "scaled. The maid will I frame and make fit for his"}, {"player": "DUKE", "playerline": "attempt. If you think well to carry this as you may,"}, {"player": "DUKE", "playerline": "the doubleness of the benefit defends the deceit"}, {"player": "DUKE", "playerline": "from reproof. What think you of it?"}, {"player": "ISABELLA", "playerline": "The image of it gives me content already, and"}, {"player": "ISABELLA", "playerline": "I trust it will grow to a most prosperous perfection."}, {"player": "DUKE", "playerline": "It lies much in your holding up. Haste"}, {"player": "DUKE", "playerline": "you speedily to Angelo. If for this night he entreat"}, {"player": "DUKE", "playerline": "you to his bed, give him promise of satisfaction. I"}, {"player": "DUKE", "playerline": "will presently to Saint Luke's. There at the moated"}, {"player": "DUKE", "playerline": "grange resides this dejected Mariana. At that place"}, {"player": "DUKE", "playerline": "call upon me, and dispatch with Angelo that it may"}, {"player": "DUKE", "playerline": "be quickly."}, {"player": "ISABELLA", "playerline": "I thank you for this comfort. Fare you well,"}, {"player": "ISABELLA", "playerline": "good father."}, {"player": "DIRECTION", "playerline": "[She exits. The Duke remains.]"}]