[{"player": "SCENE", "playerline": "SCENE III"}, {"player": "DIRECTION", "playerline": "[Enter Sir Toby and Maria.]"}, {"player": "TOBY", "playerline": "What a plague means my niece to take the death"}, {"player": "TOBY", "playerline": "of her brother thus? I am sure care's an enemy to life."}, {"player": "MARIA", "playerline": "By my troth, Sir Toby, you must come in earlier"}, {"player": "MARIA", "playerline": "o' nights. Your cousin, my lady, takes great exceptions"}, {"player": "MARIA", "playerline": "to your ill hours."}, {"player": "TOBY", "playerline": "Why, let her except before excepted!"}, {"player": "MARIA", "playerline": "Ay, but you must confine yourself within the"}, {"player": "MARIA", "playerline": "modest limits of order."}, {"player": "TOBY", "playerline": "Confine? I'll confine myself no finer than I am."}, {"player": "TOBY", "playerline": "These clothes are good enough to drink in, and so"}, {"player": "TOBY", "playerline": "be these boots too. An they be not, let them hang"}, {"player": "TOBY", "playerline": "themselves in their own straps!"}, {"player": "MARIA", "playerline": "That quaffing and drinking will undo you. I"}, {"player": "MARIA", "playerline": "heard my lady talk of it yesterday, and of a foolish"}, {"player": "MARIA", "playerline": "knight that you brought in one night here to be her wooer."}, {"player": "TOBY", "playerline": "Who, Sir Andrew Aguecheek?"}, {"player": "MARIA", "playerline": "Ay, he."}, {"player": "TOBY", "playerline": "He's as tall a man as any 's in Illyria."}, {"player": "MARIA", "playerline": "What's that to th' purpose?"}, {"player": "TOBY", "playerline": "Why, he has three thousand ducats a year!"}, {"player": "MARIA", "playerline": "Ay, but he'll have but a year in all these ducats."}, {"player": "MARIA", "playerline": "He's a very fool and a prodigal."}, {"player": "TOBY", "playerline": "Fie that you'll say so! He plays o' th' viol-de-gamboys"}, {"player": "TOBY", "playerline": "and speaks three or four languages word"}, {"player": "TOBY", "playerline": "for word without book, and hath all the good gifts of nature."}, {"player": "MARIA", "playerline": "He hath indeed, almost natural, for, besides"}, {"player": "MARIA", "playerline": "that he's a fool, he's a great quarreler, and, but that"}, {"player": "MARIA", "playerline": "he hath the gift of a coward to allay the gust he hath"}, {"player": "MARIA", "playerline": "in quarreling, 'tis thought among the prudent he"}, {"player": "MARIA", "playerline": "would quickly have the gift of a grave."}, {"player": "TOBY", "playerline": "By this hand, they are scoundrels and substractors"}, {"player": "TOBY", "playerline": "that say so of him. Who are they?"}, {"player": "MARIA", "playerline": "They that add, moreover, he's drunk nightly in"}, {"player": "MARIA", "playerline": "your company."}, {"player": "TOBY", "playerline": "With drinking healths to my niece. I'll drink to"}, {"player": "TOBY", "playerline": "her as long as there is a passage in my throat and"}, {"player": "TOBY", "playerline": "drink in Illyria. He's a coward and a coistrel that"}, {"player": "TOBY", "playerline": "will not drink to my niece till his brains turn o' th'"}, {"player": "TOBY", "playerline": "toe like a parish top. What, wench! Castiliano vulgo,"}, {"player": "TOBY", "playerline": "for here comes Sir Andrew Agueface."}, {"player": "DIRECTION", "playerline": "[Enter Sir Andrew.]"}, {"player": "ANDREW", "playerline": "Sir Toby Belch! How now, Sir Toby Belch?"}, {"player": "TOBY", "playerline": "Sweet Sir Andrew!"}, {"player": "ANDREW", "playerline": "Bless you, fair shrew."}, {"player": "MARIA", "playerline": "And you too, sir."}, {"player": "TOBY", "playerline": "Accost, Sir Andrew, accost!"}, {"player": "ANDREW", "playerline": "What's that?"}, {"player": "TOBY", "playerline": "My niece's chambermaid."}, {"player": "ANDREW", "playerline": "Good Mistress Accost, I desire better acquaintance."}, {"player": "MARIA", "playerline": "My name is Mary, sir."}, {"player": "ANDREW", "playerline": "Good Mistress Mary Accost--"}, {"player": "TOBY", "playerline": "You mistake, knight. 'Accost' is front her, board"}, {"player": "TOBY", "playerline": "her, woo her, assail her."}, {"player": "ANDREW", "playerline": "By my troth, I would not undertake her in"}, {"player": "ANDREW", "playerline": "this company. Is that the meaning of 'accost'?"}, {"player": "MARIA", "playerline": "Fare you well, gentlemen."}, {"player": "DIRECTION", "playerline": "[She begins to exit.]"}, {"player": "TOBY", "playerline": "An thou let part so, Sir Andrew, would thou"}, {"player": "TOBY", "playerline": "mightst never draw sword again."}, {"player": "ANDREW", "playerline": "An you part so, mistress, I would I might"}, {"player": "ANDREW", "playerline": "never draw sword again. Fair lady, do you think you"}, {"player": "ANDREW", "playerline": "have fools in hand?"}, {"player": "MARIA", "playerline": "Sir, I have not you by th' hand."}, {"player": "ANDREW", "playerline": "Marry, but you shall have, and here's my hand."}, {"player": "DIRECTION", "playerline": "[He offers his hand.]"}, {"player": "MARIA", "playerline": "Now sir, thought is free. I"}, {"player": "MARIA", "playerline": "pray you, bring your hand to th' butt'ry bar and let"}, {"player": "MARIA", "playerline": "it drink."}, {"player": "ANDREW", "playerline": "Wherefore, sweetheart? What's your metaphor?"}, {"player": "MARIA", "playerline": "It's dry, sir."}, {"player": "ANDREW", "playerline": "Why, I think so. I am not such an ass but I"}, {"player": "ANDREW", "playerline": "can keep my hand dry. But what's your jest?"}, {"player": "MARIA", "playerline": "A dry jest, sir."}, {"player": "ANDREW", "playerline": "Are you full of them?"}, {"player": "MARIA", "playerline": "Ay, sir, I have them at my fingers' ends. Marry,"}, {"player": "MARIA", "playerline": "now I let go your hand, I am barren."}, {"player": "DIRECTION", "playerline": "[Maria exits.]"}, {"player": "TOBY", "playerline": "O knight, thou lack'st a cup of canary! When did"}, {"player": "TOBY", "playerline": "I see thee so put down?"}, {"player": "ANDREW", "playerline": "Never in your life, I think, unless you see"}, {"player": "ANDREW", "playerline": "canary put me down. Methinks sometimes I have"}, {"player": "ANDREW", "playerline": "no more wit than a Christian or an ordinary man"}, {"player": "ANDREW", "playerline": "has. But I am a great eater of beef, and I believe that"}, {"player": "ANDREW", "playerline": "does harm to my wit."}, {"player": "TOBY", "playerline": "No question."}, {"player": "ANDREW", "playerline": "An I thought that, I'd forswear it. I'll ride"}, {"player": "ANDREW", "playerline": "home tomorrow, Sir Toby."}, {"player": "TOBY", "playerline": "Pourquoi, my dear knight?"}, {"player": "ANDREW", "playerline": "What is 'pourquoi'? Do, or not do? I would I"}, {"player": "ANDREW", "playerline": "had bestowed that time in the tongues that I have in"}, {"player": "ANDREW", "playerline": "fencing, dancing, and bearbaiting. O, had I but"}, {"player": "ANDREW", "playerline": "followed the arts!"}, {"player": "TOBY", "playerline": "Then hadst thou had an excellent head of hair."}, {"player": "ANDREW", "playerline": "Why, would that have mended my hair?"}, {"player": "TOBY", "playerline": "Past question, for thou seest it will not curl by nature."}, {"player": "ANDREW", "playerline": "But it becomes me well enough, does 't not?"}, {"player": "TOBY", "playerline": "Excellent! It hangs like flax on a distaff, and I"}, {"player": "TOBY", "playerline": "hope to see a huswife take thee between her legs"}, {"player": "TOBY", "playerline": "and spin it off."}, {"player": "ANDREW", "playerline": "Faith, I'll home tomorrow, Sir Toby. Your"}, {"player": "ANDREW", "playerline": "niece will not be seen, or if she be, it's four to one"}, {"player": "ANDREW", "playerline": "she'll none of me. The Count himself here hard by"}, {"player": "ANDREW", "playerline": "woos her."}, {"player": "TOBY", "playerline": "She'll none o' th' Count. She'll not match above"}, {"player": "TOBY", "playerline": "her degree, neither in estate, years, nor wit. I have"}, {"player": "TOBY", "playerline": "heard her swear 't. Tut, there's life in 't, man."}, {"player": "ANDREW", "playerline": "I'll stay a month longer. I am a fellow o' th'"}, {"player": "ANDREW", "playerline": "strangest mind i' th' world. I delight in masques"}, {"player": "ANDREW", "playerline": "and revels sometimes altogether."}, {"player": "TOBY", "playerline": "Art thou good at these kickshawses, knight?"}, {"player": "ANDREW", "playerline": "As any man in Illyria, whatsoever he be,"}, {"player": "ANDREW", "playerline": "under the degree of my betters, and yet I will not"}, {"player": "ANDREW", "playerline": "compare with an old man."}, {"player": "TOBY", "playerline": "What is thy excellence in a galliard, knight?"}, {"player": "ANDREW", "playerline": "Faith, I can cut a caper."}, {"player": "TOBY", "playerline": "And I can cut the mutton to 't."}, {"player": "ANDREW", "playerline": "And I think I have the back-trick simply as"}, {"player": "ANDREW", "playerline": "strong as any man in Illyria."}, {"player": "TOBY", "playerline": "Wherefore are these things hid? Wherefore have"}, {"player": "TOBY", "playerline": "these gifts a curtain before 'em? Are they like to"}, {"player": "TOBY", "playerline": "take dust, like Mistress Mall's picture? Why dost"}, {"player": "TOBY", "playerline": "thou not go to church in a galliard and come home"}, {"player": "TOBY", "playerline": "in a coranto? My very walk should be a jig. I would"}, {"player": "TOBY", "playerline": "not so much as make water but in a sink-a-pace."}, {"player": "TOBY", "playerline": "What dost thou mean? Is it a world to hide virtues"}, {"player": "TOBY", "playerline": "in? I did think, by the excellent constitution of thy"}, {"player": "TOBY", "playerline": "leg, it was formed under the star of a galliard."}, {"player": "ANDREW", "playerline": "Ay, 'tis strong, and it does indifferent well in a"}, {"player": "ANDREW", "playerline": "dun-colored stock. Shall we set about some revels?"}, {"player": "TOBY", "playerline": "What shall we do else? Were we not born under Taurus?"}, {"player": "ANDREW", "playerline": "Taurus? That's sides and heart."}, {"player": "TOBY", "playerline": "No, sir, it is legs and thighs. Let me see thee"}, {"player": "TOBY", "playerline": "caper. [Sir Andrew dances.] Ha, higher! Ha, ha, excellent!"}, {"player": "DIRECTION", "playerline": "[They exit.]"}]