[{"player": "SCENE", "playerline": "SCENE V"}, {"player": "DIRECTION", "playerline": "[Here an alarum again, and Talbot pursueth the"}, {"player": "DIRECTION", "playerline": "Dauphin and driveth him; then enter Joan la Pucelle,"}, {"player": "DIRECTION", "playerline": "driving Englishmen before her. They cross the stage"}, {"player": "DIRECTION", "playerline": "and exit. Then enter Talbot.]"}, {"player": "TALBOT", "playerline": "Where is my strength, my valor, and my force?"}, {"player": "TALBOT", "playerline": "Our English troops retire; I cannot stay them."}, {"player": "TALBOT", "playerline": "A woman clad in armor chaseth them."}, {"player": "DIRECTION", "playerline": "[Enter Pucelle, with Soldiers.]"}, {"player": "TALBOT", "playerline": "Here, here she comes!--I'll have a bout with thee."}, {"player": "TALBOT", "playerline": "Devil or devil's dam, I'll conjure thee."}, {"player": "TALBOT", "playerline": "Blood will I draw on thee--thou art a witch--"}, {"player": "TALBOT", "playerline": "And straightway give thy soul to him thou serv'st."}, {"player": "PUCELLE", "playerline": "Come, come; 'tis only I that must disgrace thee."}, {"player": "DIRECTION", "playerline": "[Here they fight.]"}, {"player": "TALBOT", "playerline": "Heavens, can you suffer hell so to prevail?"}, {"player": "TALBOT", "playerline": "My breast I'll burst with straining of my courage,"}, {"player": "TALBOT", "playerline": "And from my shoulders crack my arms asunder,"}, {"player": "TALBOT", "playerline": "But I will chastise this high-minded strumpet."}, {"player": "DIRECTION", "playerline": "[They fight again.]"}, {"player": "PUCELLE", "playerline": "Talbot, farewell. Thy hour is not yet come."}, {"player": "PUCELLE", "playerline": "I must go victual Orleance forthwith."}, {"player": "DIRECTION", "playerline": "[A short alarum. Then she prepares to"}, {"player": "DIRECTION", "playerline": "enter the town with Soldiers.]"}, {"player": "DIRECTION", "playerline": "O'ertake me if thou canst. I scorn thy strength."}, {"player": "DIRECTION", "playerline": "Go, go, cheer up thy hunger-starved men."}, {"player": "DIRECTION", "playerline": "Help Salisbury to make his testament."}, {"player": "DIRECTION", "playerline": "This day is ours, as many more shall be."}, {"player": "DIRECTION", "playerline": "[She exits with Soldiers.]"}, {"player": "TALBOT", "playerline": "My thoughts are whirled like a potter's wheel."}, {"player": "TALBOT", "playerline": "I know not where I am nor what I do."}, {"player": "TALBOT", "playerline": "A witch by fear--not force, like Hannibal--"}, {"player": "TALBOT", "playerline": "Drives back our troops, and conquers as she lists."}, {"player": "TALBOT", "playerline": "So bees with smoke and doves with noisome stench"}, {"player": "TALBOT", "playerline": "Are from their hives and houses driven away."}, {"player": "TALBOT", "playerline": "They called us, for our fierceness, English dogs;"}, {"player": "TALBOT", "playerline": "Now like to whelps we crying run away."}, {"player": "DIRECTION", "playerline": "[A short alarum. Enter English soldiers,"}, {"player": "DIRECTION", "playerline": "chased by French soldiers.]"}, {"player": "DIRECTION", "playerline": "Hark, countrymen, either renew the fight,"}, {"player": "DIRECTION", "playerline": "Or tear the lions out of England's coat."}, {"player": "DIRECTION", "playerline": "Renounce your soil; give sheep in lions' stead."}, {"player": "DIRECTION", "playerline": "Sheep run not half so treacherous from the wolf,"}, {"player": "DIRECTION", "playerline": "Or horse or oxen from the leopard,"}, {"player": "DIRECTION", "playerline": "As you fly from your oft-subdued slaves."}, {"player": "DIRECTION", "playerline": "[Alarum. Here another skirmish.]"}, {"player": "DIRECTION", "playerline": "It will not be! Retire into your trenches."}, {"player": "DIRECTION", "playerline": "You all consented unto Salisbury's death,"}, {"player": "DIRECTION", "playerline": "For none would strike a stroke in his revenge."}, {"player": "DIRECTION", "playerline": "Pucelle is entered into Orleance"}, {"player": "DIRECTION", "playerline": "In spite of us or aught that we could do."}, {"player": "DIRECTION", "playerline": "[Soldiers exit.]"}, {"player": "DIRECTION", "playerline": "O, would I were to die with Salisbury!"}, {"player": "DIRECTION", "playerline": "The shame hereof will make me hide my head."}, {"player": "DIRECTION", "playerline": "[Talbot exits. Alarum. Retreat.]"}]