[{"player": "SCENE", "playerline": "SCENE V"}, {"player": "DIRECTION", "playerline": "[Enter Ajax, armed, Achilles, Patroclus, Agamemnon,"}, {"player": "DIRECTION", "playerline": "Menelaus, Ulysses, Nestor, etc. and Trumpeter.]"}, {"player": "AGAMEMNON", "playerline": "Here art thou in appointment fresh and fair,"}, {"player": "AGAMEMNON", "playerline": "Anticipating time with starting courage."}, {"player": "AGAMEMNON", "playerline": "Give with thy trumpet a loud note to Troy,"}, {"player": "AGAMEMNON", "playerline": "Thou dreadful Ajax, that the appalled air"}, {"player": "AGAMEMNON", "playerline": "May pierce the head of the great combatant"}, {"player": "AGAMEMNON", "playerline": "And hale him hither."}, {"player": "AJAX", "playerline": "Thou, trumpet, there's my purse."}, {"player": "DIRECTION", "playerline": "[He gives money to Trumpeter.]"}, {"player": "AJAX", "playerline": "Now crack thy lungs and split thy brazen pipe."}, {"player": "AJAX", "playerline": "Blow, villain, till thy sphered bias cheek"}, {"player": "AJAX", "playerline": "Outswell the colic of puffed Aquilon."}, {"player": "AJAX", "playerline": "Come, stretch thy chest, and let thy eyes spout blood."}, {"player": "AJAX", "playerline": "Thou blowest for Hector."}, {"player": "DIRECTION", "playerline": "[Sound trumpet.]"}, {"player": "ULYSSES", "playerline": "No trumpet answers."}, {"player": "ACHILLES", "playerline": "'Tis but early days."}, {"player": "DIRECTION", "playerline": "[Enter Cressida and Diomedes.]"}, {"player": "AGAMEMNON", "playerline": "Is not yond Diomed with Calchas' daughter?"}, {"player": "ULYSSES", "playerline": "'Tis he. I ken the manner of his gait."}, {"player": "ULYSSES", "playerline": "He rises on the toe; that spirit of his"}, {"player": "ULYSSES", "playerline": "In aspiration lifts him from the earth."}, {"player": "AGAMEMNON", "playerline": "Is this the Lady Cressid?"}, {"player": "DIOMEDES", "playerline": "Even she."}, {"player": "AGAMEMNON", "playerline": "Most dearly welcome to the Greeks, sweet lady."}, {"player": "DIRECTION", "playerline": "[He kisses her.]"}, {"player": "NESTOR", "playerline": "Our general doth salute you with a kiss."}, {"player": "ULYSSES", "playerline": "Yet is the kindness but particular."}, {"player": "ULYSSES", "playerline": "'Twere better she were kissed in general."}, {"player": "NESTOR", "playerline": "And very courtly counsel. I'll begin."}, {"player": "DIRECTION", "playerline": "[He kisses her.]"}, {"player": "NESTOR", "playerline": "So much for Nestor."}, {"player": "ACHILLES", "playerline": "I'll take that winter from your lips, fair lady."}, {"player": "ACHILLES", "playerline": "Achilles bids you welcome."}, {"player": "DIRECTION", "playerline": "[He kisses her.]"}, {"player": "MENELAUS", "playerline": "I had good argument for kissing once."}, {"player": "PATROCLUS", "playerline": "But that's no argument for kissing now,"}, {"player": "PATROCLUS", "playerline": "For thus popped Paris in his hardiment"}, {"player": "PATROCLUS", "playerline": "And parted thus you and your argument."}, {"player": "DIRECTION", "playerline": "[He kisses her.]"}, {"player": "ULYSSES", "playerline": "O deadly gall and theme of all our scorns,"}, {"player": "ULYSSES", "playerline": "For which we lose our heads to gild his horns!"}, {"player": "PATROCLUS", "playerline": "The first was Menelaus' kiss; this mine."}, {"player": "PATROCLUS", "playerline": "Patroclus kisses you."}, {"player": "DIRECTION", "playerline": "[He kisses her again.]"}, {"player": "MENELAUS", "playerline": "O, this is trim!"}, {"player": "PATROCLUS", "playerline": "Paris and I kiss evermore for him."}, {"player": "MENELAUS", "playerline": "I'll have my kiss, sir.--Lady, by your leave."}, {"player": "CRESSIDA", "playerline": "In kissing, do you render or receive?"}, {"player": "MENELAUS", "playerline": "Both take and give."}, {"player": "CRESSIDA", "playerline": "I'll make my match to live,"}, {"player": "CRESSIDA", "playerline": "The kiss you take is better than you give."}, {"player": "CRESSIDA", "playerline": "Therefore no kiss."}, {"player": "MENELAUS", "playerline": "I'll give you boot: I'll give you three for one."}, {"player": "CRESSIDA", "playerline": "You are an odd man. Give even, or give none."}, {"player": "MENELAUS", "playerline": "An odd man, lady? Every man is odd."}, {"player": "CRESSIDA", "playerline": "No, Paris is not, for you know 'tis true"}, {"player": "CRESSIDA", "playerline": "That you are odd, and he is even with you."}, {"player": "MENELAUS", "playerline": "You fillip me o' th' head."}, {"player": "CRESSIDA", "playerline": "No, I'll be sworn."}, {"player": "ULYSSES", "playerline": "It were no match, your nail against his horn."}, {"player": "ULYSSES", "playerline": "May I, sweet lady, beg a kiss of you?"}, {"player": "CRESSIDA", "playerline": "You may."}, {"player": "ULYSSES", "playerline": "I do desire it."}, {"player": "CRESSIDA", "playerline": "Why, beg two."}, {"player": "ULYSSES", "playerline": "Why, then, for Venus' sake, give me a kiss"}, {"player": "ULYSSES", "playerline": "When Helen is a maid again and his."}, {"player": "CRESSIDA", "playerline": "I am your debtor; claim it when 'tis due."}, {"player": "ULYSSES", "playerline": "Never's my day, and then a kiss of you."}, {"player": "DIOMEDES", "playerline": "Lady, a word. I'll bring you to your father."}, {"player": "DIRECTION", "playerline": "[Diomedes and Cressida talk aside.]"}, {"player": "NESTOR", "playerline": "A woman of quick sense."}, {"player": "ULYSSES", "playerline": "Fie, fie upon her!"}, {"player": "ULYSSES", "playerline": "There's language in her eye, her cheek, her lip;"}, {"player": "ULYSSES", "playerline": "Nay, her foot speaks. Her wanton spirits look out"}, {"player": "ULYSSES", "playerline": "At every joint and motive of her body."}, {"player": "ULYSSES", "playerline": "O, these encounterers, so glib of tongue,"}, {"player": "ULYSSES", "playerline": "That give accosting welcome ere it comes"}, {"player": "ULYSSES", "playerline": "And wide unclasp the tables of their thoughts"}, {"player": "ULYSSES", "playerline": "To every tickling reader! Set them down"}, {"player": "ULYSSES", "playerline": "For sluttish spoils of opportunity"}, {"player": "ULYSSES", "playerline": "And daughters of the game."}, {"player": "DIRECTION", "playerline": "[Diomedes and Cressida exit.]"}, {"player": "DIRECTION", "playerline": "[Flourish.]"}, {"player": "ALL", "playerline": "The Trojan's trumpet."}, {"player": "DIRECTION", "playerline": "[Enter all of Troy: Hector, armed, Paris, Aeneas,"}, {"player": "DIRECTION", "playerline": "Helenus, Troilus, and Attendants.]"}, {"player": "AGAMEMNON", "playerline": "Yonder comes the troop."}, {"player": "AENEAS", "playerline": "Hail, all the state of Greece! What shall be done"}, {"player": "AENEAS", "playerline": "To him that victory commands? Or do you purpose"}, {"player": "AENEAS", "playerline": "A victor shall be known? Will you the knights"}, {"player": "AENEAS", "playerline": "Shall to the edge of all extremity"}, {"player": "AENEAS", "playerline": "Pursue each other, or shall they be divided"}, {"player": "AENEAS", "playerline": "By any voice or order of the field?"}, {"player": "AENEAS", "playerline": "Hector bade ask."}, {"player": "AGAMEMNON", "playerline": "Which way would Hector have it?"}, {"player": "AENEAS", "playerline": "He cares not; he'll obey conditions."}, {"player": "AGAMEMNON", "playerline": "'Tis done like Hector."}, {"player": "ACHILLES", "playerline": "But securely done,"}, {"player": "ACHILLES", "playerline": "A little proudly, and great deal misprizing"}, {"player": "ACHILLES", "playerline": "The knight opposed."}, {"player": "AENEAS", "playerline": "If not Achilles, sir,"}, {"player": "AENEAS", "playerline": "What is your name?"}, {"player": "ACHILLES", "playerline": "If not Achilles, nothing."}, {"player": "AENEAS", "playerline": "Therefore Achilles. But whate'er, know this:"}, {"player": "AENEAS", "playerline": "In the extremity of great and little,"}, {"player": "AENEAS", "playerline": "Valor and pride excel themselves in Hector,"}, {"player": "AENEAS", "playerline": "The one almost as infinite as all,"}, {"player": "AENEAS", "playerline": "The other blank as nothing. Weigh him well,"}, {"player": "AENEAS", "playerline": "And that which looks like pride is courtesy."}, {"player": "AENEAS", "playerline": "This Ajax is half made of Hector's blood,"}, {"player": "AENEAS", "playerline": "In love whereof half Hector stays at home;"}, {"player": "AENEAS", "playerline": "Half heart, half hand, half Hector comes to seek"}, {"player": "AENEAS", "playerline": "This blended knight, half Trojan and half Greek."}, {"player": "ACHILLES", "playerline": "A maiden battle, then? O, I perceive you."}, {"player": "DIRECTION", "playerline": "[Enter Diomedes.]"}, {"player": "AGAMEMNON", "playerline": "Here is Sir Diomed.--Go, gentle knight;"}, {"player": "AGAMEMNON", "playerline": "Stand by our Ajax. As you and Lord Aeneas"}, {"player": "AGAMEMNON", "playerline": "Consent upon the order of their fight,"}, {"player": "AGAMEMNON", "playerline": "So be it, either to the uttermost"}, {"player": "AGAMEMNON", "playerline": "Or else a breath. The combatants being kin"}, {"player": "AGAMEMNON", "playerline": "Half stints their strife before their strokes begin."}, {"player": "DIRECTION", "playerline": "[Hector and Ajax enter the lists.]"}, {"player": "ULYSSES", "playerline": "They are opposed already."}, {"player": "AGAMEMNON", "playerline": "What Trojan is that same that looks so heavy?"}, {"player": "ULYSSES", "playerline": "The youngest son of Priam, a true knight,"}, {"player": "ULYSSES", "playerline": "Not yet mature, yet matchless firm of word,"}, {"player": "ULYSSES", "playerline": "Speaking in deeds, and deedless in his tongue,"}, {"player": "ULYSSES", "playerline": "Not soon provoked, nor being provoked soon calmed,"}, {"player": "ULYSSES", "playerline": "His heart and hand both open and both free."}, {"player": "ULYSSES", "playerline": "For what he has, he gives; what thinks, he shows;"}, {"player": "ULYSSES", "playerline": "Yet gives he not till judgment guide his bounty,"}, {"player": "ULYSSES", "playerline": "Nor dignifies an impair thought with breath;"}, {"player": "ULYSSES", "playerline": "Manly as Hector, but more dangerous,"}, {"player": "ULYSSES", "playerline": "For Hector in his blaze of wrath subscribes"}, {"player": "ULYSSES", "playerline": "To tender objects, but he in heat of action"}, {"player": "ULYSSES", "playerline": "Is more vindicative than jealous love."}, {"player": "ULYSSES", "playerline": "They call him Troilus, and on him erect"}, {"player": "ULYSSES", "playerline": "A second hope, as fairly built as Hector."}, {"player": "ULYSSES", "playerline": "Thus says Aeneas, one that knows the youth"}, {"player": "ULYSSES", "playerline": "Even to his inches, and with private soul"}, {"player": "ULYSSES", "playerline": "Did in great Ilium thus translate him to me."}, {"player": "DIRECTION", "playerline": "[Alarum. The fight begins.]"}, {"player": "AGAMEMNON", "playerline": "They are in action."}, {"player": "NESTOR", "playerline": "Now, Ajax, hold thine own!"}, {"player": "TROILUS", "playerline": "Hector, thou sleep'st. Awake thee!"}, {"player": "AGAMEMNON", "playerline": "His blows are well disposed.--There, Ajax!"}, {"player": "DIRECTION", "playerline": "[Trumpets cease.]"}, {"player": "DIOMEDES", "playerline": "You must no more."}, {"player": "AENEAS", "playerline": "Princes, enough, so please you."}, {"player": "AJAX", "playerline": "I am not warm yet. Let us fight again."}, {"player": "DIOMEDES", "playerline": "As Hector pleases."}, {"player": "HECTOR", "playerline": "Why, then, will I no more.--"}, {"player": "HECTOR", "playerline": "Thou art, great lord, my father's sister's son,"}, {"player": "HECTOR", "playerline": "A cousin-german to great Priam's seed."}, {"player": "HECTOR", "playerline": "The obligation of our blood forbids"}, {"player": "HECTOR", "playerline": "A gory emulation 'twixt us twain."}, {"player": "HECTOR", "playerline": "Were thy commixtion Greek and Trojan so"}, {"player": "HECTOR", "playerline": "That thou couldst say 'This hand is Grecian all,"}, {"player": "HECTOR", "playerline": "And this is Trojan; the sinews of this leg"}, {"player": "HECTOR", "playerline": "All Greek, and this all Troy; my mother's blood"}, {"player": "HECTOR", "playerline": "Runs on the dexter cheek, and this sinister"}, {"player": "HECTOR", "playerline": "Bounds in my father's,' by Jove multipotent,"}, {"player": "HECTOR", "playerline": "Thou shouldst not bear from me a Greekish member"}, {"player": "HECTOR", "playerline": "Wherein my sword had not impressure made"}, {"player": "HECTOR", "playerline": "Of our rank feud. But the just gods gainsay"}, {"player": "HECTOR", "playerline": "That any drop thou borrowd'st from thy mother,"}, {"player": "HECTOR", "playerline": "My sacred aunt, should by my mortal sword"}, {"player": "HECTOR", "playerline": "Be drained. Let me embrace thee, Ajax."}, {"player": "HECTOR", "playerline": "By him that thunders, thou hast lusty arms!"}, {"player": "HECTOR", "playerline": "Hector would have them fall upon him thus."}, {"player": "HECTOR", "playerline": "Cousin, all honor to thee!"}, {"player": "DIRECTION", "playerline": "[They embrace.]"}, {"player": "AJAX", "playerline": "I thank thee, Hector."}, {"player": "AJAX", "playerline": "Thou art too gentle and too free a man."}, {"player": "AJAX", "playerline": "I came to kill thee, cousin, and bear hence"}, {"player": "AJAX", "playerline": "A great addition earned in thy death."}, {"player": "HECTOR", "playerline": "Not Neoptolemus so mirable--"}, {"player": "HECTOR", "playerline": "On whose bright crest Fame with her loud'st 'Oyez'"}, {"player": "HECTOR", "playerline": "Cries 'This is he'--could promise to himself"}, {"player": "HECTOR", "playerline": "A thought of added honor torn from Hector."}, {"player": "AENEAS", "playerline": "There is expectance here from both the sides"}, {"player": "AENEAS", "playerline": "What further you will do."}, {"player": "HECTOR", "playerline": "We'll answer it;"}, {"player": "HECTOR", "playerline": "The issue is embracement.--Ajax, farewell."}, {"player": "DIRECTION", "playerline": "[They embrace again.]"}, {"player": "AJAX", "playerline": "If I might in entreaties find success,"}, {"player": "AJAX", "playerline": "As seld I have the chance, I would desire"}, {"player": "AJAX", "playerline": "My famous cousin to our Grecian tents."}, {"player": "DIOMEDES", "playerline": "'Tis Agamemnon's wish; and great Achilles"}, {"player": "DIOMEDES", "playerline": "Doth long to see unarmed the valiant Hector."}, {"player": "HECTOR", "playerline": "Aeneas, call my brother Troilus to me,"}, {"player": "HECTOR", "playerline": "And signify this loving interview"}, {"player": "HECTOR", "playerline": "To the expecters of our Trojan part;"}, {"player": "HECTOR", "playerline": "Desire them home."}, {"player": "DIRECTION", "playerline": "[Aeneas speaks to Trojans, who exit; he then"}, {"player": "DIRECTION", "playerline": "returns with Troilus.]"}, {"player": "DIRECTION", "playerline": "[To Ajax.] Give me thy hand, my cousin."}, {"player": "DIRECTION", "playerline": "I will go eat with thee and see your knights."}, {"player": "DIRECTION", "playerline": "[Agamemnon and the rest come forward.]"}, {"player": "AJAX", "playerline": "Great Agamemnon comes to meet us here."}, {"player": "HECTOR", "playerline": "The worthiest of them tell me name by name;"}, {"player": "HECTOR", "playerline": "But for Achilles, my own searching eyes"}, {"player": "HECTOR", "playerline": "Shall find him by his large and portly size."}, {"player": "AGAMEMNON", "playerline": "Worthy all arms! As welcome as to one"}, {"player": "AGAMEMNON", "playerline": "That would be rid of such an enemy--"}, {"player": "AGAMEMNON", "playerline": "But that's no welcome. Understand more clear:"}, {"player": "AGAMEMNON", "playerline": "What's past and what's to come is strewed with husks"}, {"player": "AGAMEMNON", "playerline": "And formless ruin of oblivion;"}, {"player": "AGAMEMNON", "playerline": "But in this extant moment, faith and troth,"}, {"player": "AGAMEMNON", "playerline": "Strained purely from all hollow bias-drawing,"}, {"player": "AGAMEMNON", "playerline": "Bids thee, with most divine integrity,"}, {"player": "AGAMEMNON", "playerline": "From heart of very heart, great Hector, welcome."}, {"player": "HECTOR", "playerline": "I thank thee, most imperious Agamemnon."}, {"player": "AGAMEMNON", "playerline": "My well-famed lord of Troy, no less to you."}, {"player": "MENELAUS", "playerline": "Let me confirm my princely brother's greeting:"}, {"player": "MENELAUS", "playerline": "You brace of warlike brothers, welcome hither."}, {"player": "HECTOR", "playerline": "Who must we answer?"}, {"player": "AENEAS", "playerline": "The noble Menelaus."}, {"player": "HECTOR", "playerline": "O, you, my lord? By Mars his gauntlet, thanks!"}, {"player": "HECTOR", "playerline": "Mock not that I affect th' untraded oath;"}, {"player": "HECTOR", "playerline": "Your quondam wife swears still by Venus' glove."}, {"player": "HECTOR", "playerline": "She's well, but bade me not commend her to you."}, {"player": "MENELAUS", "playerline": "Name her not now, sir; she's a deadly theme."}, {"player": "HECTOR", "playerline": "O, pardon! I offend."}, {"player": "NESTOR", "playerline": "I have, thou gallant Trojan, seen thee oft,"}, {"player": "NESTOR", "playerline": "Laboring for destiny, make cruel way"}, {"player": "NESTOR", "playerline": "Through ranks of Greekish youth; and I have seen thee,"}, {"player": "NESTOR", "playerline": "As hot as Perseus, spur thy Phrygian steed,"}, {"player": "NESTOR", "playerline": "Despising many forfeits and subduments,"}, {"player": "NESTOR", "playerline": "When thou hast hung thy advanced sword i' th' air,"}, {"player": "NESTOR", "playerline": "Not letting it decline on the declined,"}, {"player": "NESTOR", "playerline": "That I have said to some my standers-by"}, {"player": "NESTOR", "playerline": "'Lo, Jupiter is yonder, dealing life!'"}, {"player": "NESTOR", "playerline": "And I have seen thee pause and take thy breath"}, {"player": "NESTOR", "playerline": "When that a ring of Greeks have hemmed thee in,"}, {"player": "NESTOR", "playerline": "Like an Olympian wrestling. This have I seen."}, {"player": "NESTOR", "playerline": "But this thy countenance, still locked in steel,"}, {"player": "NESTOR", "playerline": "I never saw till now. I knew thy grandsire"}, {"player": "NESTOR", "playerline": "And once fought with him; he was a soldier good,"}, {"player": "NESTOR", "playerline": "But, by great Mars, the captain of us all,"}, {"player": "NESTOR", "playerline": "Never like thee! O, let an old man embrace thee;"}, {"player": "NESTOR", "playerline": "And, worthy warrior, welcome to our tents."}, {"player": "AENEAS", "playerline": "'Tis the old Nestor."}, {"player": "HECTOR", "playerline": "Let me embrace thee, good old chronicle"}, {"player": "HECTOR", "playerline": "That hast so long walked hand in hand with time."}, {"player": "HECTOR", "playerline": "Most reverend Nestor, I am glad to clasp thee."}, {"player": "DIRECTION", "playerline": "[They embrace.]"}, {"player": "NESTOR", "playerline": "I would my arms could match thee in contention"}, {"player": "NESTOR", "playerline": "As they contend with thee in courtesy."}, {"player": "HECTOR", "playerline": "I would they could."}, {"player": "NESTOR", "playerline": "Ha! By this white beard, I'd fight with thee tomorrow."}, {"player": "NESTOR", "playerline": "Well, welcome, welcome. I have seen the time!"}, {"player": "ULYSSES", "playerline": "I wonder now how yonder city stands"}, {"player": "ULYSSES", "playerline": "When we have here her base and pillar by us."}, {"player": "HECTOR", "playerline": "I know your favor, Lord Ulysses, well."}, {"player": "HECTOR", "playerline": "Ah, sir, there's many a Greek and Trojan dead"}, {"player": "HECTOR", "playerline": "Since first I saw yourself and Diomed"}, {"player": "HECTOR", "playerline": "In Ilium, on your Greekish embassy."}, {"player": "ULYSSES", "playerline": "Sir, I foretold you then what would ensue."}, {"player": "ULYSSES", "playerline": "My prophecy is but half his journey yet,"}, {"player": "ULYSSES", "playerline": "For yonder walls, that pertly front your town,"}, {"player": "ULYSSES", "playerline": "Yon towers, whose wanton tops do buss the clouds,"}, {"player": "ULYSSES", "playerline": "Must kiss their own feet."}, {"player": "HECTOR", "playerline": "I must not believe you."}, {"player": "HECTOR", "playerline": "There they stand yet, and modestly I think"}, {"player": "HECTOR", "playerline": "The fall of every Phrygian stone will cost"}, {"player": "HECTOR", "playerline": "A drop of Grecian blood. The end crowns all,"}, {"player": "HECTOR", "playerline": "And that old common arbitrator, Time,"}, {"player": "HECTOR", "playerline": "Will one day end it."}, {"player": "ULYSSES", "playerline": "So to him we leave it."}, {"player": "ULYSSES", "playerline": "Most gentle and most valiant Hector, welcome."}, {"player": "ULYSSES", "playerline": "After the General, I beseech you next"}, {"player": "ULYSSES", "playerline": "To feast with me and see me at my tent."}, {"player": "ACHILLES", "playerline": "I shall forestall thee, Lord Ulysses, thou!--"}, {"player": "ACHILLES", "playerline": "Now, Hector, I have fed mine eyes on thee;"}, {"player": "ACHILLES", "playerline": "I have with exact view perused thee, Hector,"}, {"player": "ACHILLES", "playerline": "And quoted joint by joint."}, {"player": "HECTOR", "playerline": "Is this Achilles?"}, {"player": "ACHILLES", "playerline": "I am Achilles."}, {"player": "HECTOR", "playerline": "Stand fair, I pray thee. Let me look on thee."}, {"player": "ACHILLES", "playerline": "Behold thy fill."}, {"player": "HECTOR", "playerline": "Nay, I have done already."}, {"player": "ACHILLES", "playerline": "Thou art too brief. I will the second time,"}, {"player": "ACHILLES", "playerline": "As I would buy thee, view thee limb by limb."}, {"player": "HECTOR", "playerline": "O, like a book of sport thou 'lt read me o'er;"}, {"player": "HECTOR", "playerline": "But there's more in me than thou understand'st."}, {"player": "HECTOR", "playerline": "Why dost thou so oppress me with thine eye?"}, {"player": "ACHILLES", "playerline": "Tell me, you heavens, in which part of his body"}, {"player": "ACHILLES", "playerline": "Shall I destroy him--whether there, or there, or there--"}, {"player": "ACHILLES", "playerline": "That I may give the local wound a name"}, {"player": "ACHILLES", "playerline": "And make distinct the very breach whereout"}, {"player": "ACHILLES", "playerline": "Hector's great spirit flew. Answer me, heavens!"}, {"player": "HECTOR", "playerline": "It would discredit the blest gods, proud man,"}, {"player": "HECTOR", "playerline": "To answer such a question. Stand again."}, {"player": "HECTOR", "playerline": "Think'st thou to catch my life so pleasantly"}, {"player": "HECTOR", "playerline": "As to prenominate in nice conjecture"}, {"player": "HECTOR", "playerline": "Where thou wilt hit me dead?"}, {"player": "ACHILLES", "playerline": "I tell thee, yea."}, {"player": "HECTOR", "playerline": "Wert thou an oracle to tell me so,"}, {"player": "HECTOR", "playerline": "I'd not believe thee. Henceforth guard thee well,"}, {"player": "HECTOR", "playerline": "For I'll not kill thee there, nor there, nor there,"}, {"player": "HECTOR", "playerline": "But, by the forge that stithied Mars his helm,"}, {"player": "HECTOR", "playerline": "I'll kill thee everywhere, yea, o'er and o'er.--"}, {"player": "HECTOR", "playerline": "You wisest Grecians, pardon me this brag;"}, {"player": "HECTOR", "playerline": "His insolence draws folly from my lips."}, {"player": "HECTOR", "playerline": "But I'll endeavor deeds to match these words,"}, {"player": "HECTOR", "playerline": "Or may I never--"}, {"player": "AJAX", "playerline": "Do not chafe thee, cousin.--"}, {"player": "AJAX", "playerline": "And you, Achilles, let these threats alone"}, {"player": "AJAX", "playerline": "Till accident or purpose bring you to 't."}, {"player": "AJAX", "playerline": "You may have every day enough of Hector"}, {"player": "AJAX", "playerline": "If you have stomach. The general state, I fear,"}, {"player": "AJAX", "playerline": "Can scarce entreat you to be odd with him."}, {"player": "HECTOR", "playerline": "I pray you, let us see you in the field."}, {"player": "HECTOR", "playerline": "We have had pelting wars since you refused"}, {"player": "HECTOR", "playerline": "The Grecians' cause."}, {"player": "ACHILLES", "playerline": "Dost thou entreat me, Hector?"}, {"player": "ACHILLES", "playerline": "Tomorrow do I meet thee, fell as death;"}, {"player": "ACHILLES", "playerline": "Tonight all friends."}, {"player": "HECTOR", "playerline": "Thy hand upon that match."}, {"player": "AGAMEMNON", "playerline": "First, all you peers of Greece, go to my tent;"}, {"player": "AGAMEMNON", "playerline": "There in the full convive we. Afterwards,"}, {"player": "AGAMEMNON", "playerline": "As Hector's leisure and your bounties shall"}, {"player": "AGAMEMNON", "playerline": "Concur together, severally entreat him."}, {"player": "AGAMEMNON", "playerline": "Beat loud the taborins; let the trumpets blow,"}, {"player": "AGAMEMNON", "playerline": "That this great soldier may his welcome know."}, {"player": "DIRECTION", "playerline": "[Flourish.]"}, {"player": "DIRECTION", "playerline": "[All but Troilus and Ulysses exit.]"}, {"player": "TROILUS", "playerline": "My Lord Ulysses, tell me, I beseech you,"}, {"player": "TROILUS", "playerline": "In what place of the field doth Calchas keep?"}, {"player": "ULYSSES", "playerline": "At Menelaus' tent, most princely Troilus."}, {"player": "ULYSSES", "playerline": "There Diomed doth feast with him tonight,"}, {"player": "ULYSSES", "playerline": "Who neither looks upon the heaven nor Earth,"}, {"player": "ULYSSES", "playerline": "But gives all gaze and bent of amorous view"}, {"player": "ULYSSES", "playerline": "On the fair Cressid."}, {"player": "TROILUS", "playerline": "Shall I, sweet lord, be bound to you so much,"}, {"player": "TROILUS", "playerline": "After we part from Agamemnon's tent,"}, {"player": "TROILUS", "playerline": "To bring me thither?"}, {"player": "ULYSSES", "playerline": "You shall command me, sir."}, {"player": "ULYSSES", "playerline": "As gentle tell me, of what honor was"}, {"player": "ULYSSES", "playerline": "This Cressida in Troy? Had she no lover there"}, {"player": "ULYSSES", "playerline": "That wails her absence?"}, {"player": "TROILUS", "playerline": "O sir, to such as boasting show their scars"}, {"player": "TROILUS", "playerline": "A mock is due. Will you walk on, my lord?"}, {"player": "TROILUS", "playerline": "She was beloved, she loved; she is, and doth;"}, {"player": "TROILUS", "playerline": "But still sweet love is food for Fortune's tooth."}, {"player": "DIRECTION", "playerline": "[They exit.]"}]